cpplinthook/__init__.py
cpplinthook/cpplint.py
cpplinthook/formatters.py
cpplinthook-1.5.dist-info/METADATA
cpplinthook-1.5.dist-info/WHEEL
cpplinthook-1.5.dist-info/entry_points.txt
cpplinthook-1.5.dist-info/top_level.txt
cpplinthook-1.5.dist-info/RECORD
