Metadata-Version: 2.1
Name: cpplinthook
Version: 1.5
Summary: A simple script to run cpplint as a pre-commit hook
Home-page: https://nest-source-internal.git.corp.google.com/hooks/cpplint/
Author: Eli Ribble
Author-email: eliribble@google.com
License: UNKNOWN
Platform: UNKNOWN
Requires-Python: >=3.6
Requires-Dist: precommit-diffcheck (==1.1)
Requires-Dist: six (==1.12.0)
Requires-Dist: unidiff (==0.5.5)
Provides-Extra: develop
Requires-Dist: mypy ; extra == 'develop'
Requires-Dist: nose2 ; extra == 'develop'
Requires-Dist: pylint ; extra == 'develop'
